HISTORY.rst
MANIFEST.in
README.rst
setup.py
lib/nelkit/__init__.py
lib/nelkit/exceptions.py
lib/nelkit/globals.py
lib/nelkit.egg-info/PKG-INFO
lib/nelkit.egg-info/SOURCES.txt
lib/nelkit.egg-info/dependency_links.txt
lib/nelkit.egg-info/entry_points.txt
lib/nelkit.egg-info/requires.txt
lib/nelkit.egg-info/top_level.txt
lib/nelkit/args/__init__.py
lib/nelkit/args/base.py
lib/nelkit/args/snmp.py
lib/nelkit/cli/__init__.py
lib/nelkit/cli/compare_configs.py
lib/nelkit/cli/snmp_deviceinfo.py
lib/nelkit/modules/__init__.py
lib/nelkit/modules/compare_configs/__init__.py
lib/nelkit/modules/compare_configs/settings.py
lib/nelkit/parsing/__init__.py
lib/nelkit/parsing/yaml/__init__.py
lib/nelkit/parsing/yaml/loader.py
lib/nelkit/snmp/__init__.py
lib/nelkit/snmp/handler.py