Metadata-Version: 1.1
Name: nelkit
Version: 0.0.1
Summary: A Toolkit for network engineers
Home-page: http://networklore.com/nelkit/
Author: Patrick Ogenstad
Author-email: patrick@ogenstad.com
License: Apache
Platform: UNKNOWN
Classifier: Development Status :: 4 - Beta
Classifier: Intended Audience :: Developers
Classifier: Intended Audience :: System Administrators
